optisorl/__init__.py
optisorl/backend.py
optisorl-0.2.1.dist-info/DESCRIPTION.rst
optisorl-0.2.1.dist-info/METADATA
optisorl-0.2.1.dist-info/metadata.json
optisorl-0.2.1.dist-info/RECORD
optisorl-0.2.1.dist-info/top_level.txt
optisorl-0.2.1.dist-info/WHEEL
