Metadata-Version: 2.0
Name: optisorl
Version: 0.2.1
Summary: Backend plugin for sorl-thumbnail that optimizes thumbnails
Home-page: https://github.com/peterbe/optisorl
Author: Peter Bengtsson
Author-email: mail@peterbe.com
License: BSD
Platform: UNKNOWN
Classifier: License :: OSI Approved :: BSD License
Classifier: Operating System :: OS Independent
Classifier: Programming Language :: Python :: 2.6
Classifier: Programming Language :: Python :: 2.7
Classifier: Programming Language :: Python :: 3.4
Classifier: Topic :: Software Development :: Libraries :: Python Modules
